PreJsPy.py
pre_js_py-1.2.0.dist-info/METADATA
pre_js_py-1.2.0.dist-info/WHEEL
pre_js_py-1.2.0.dist-info/top_level.txt
pre_js_py-1.2.0.dist-info/RECORD
