Metadata-Version: 2.1
Name: pre-js-py
Version: 1.2.0
Summary: Highly configurable precedence-based parser written in both Python and JavaScript
Home-page: https://github.com/tkw1536/PreJsPy
Author: Tom Wiesing
Author-email: tkw01536@gmail.com
License: MIT
Platform: UNKNOWN
Classifier: Programming Language :: Python :: 2
Classifier: Programming Language :: Python :: 3
Classifier: License :: OSI Approved :: MIT License
Classifier: Topic :: Software Development :: Libraries
Classifier: Intended Audience :: Developers
Classifier: Topic :: Utilities
